wx/WebView2Loader.dll
wx/__init__.py
wx/__version__.py
wx/_adv.cp312-win_arm64.pyd
wx/_aui.cp312-win_arm64.pyd
wx/_core.cp312-win_arm64.pyd
wx/_dataview.cp312-win_arm64.pyd
wx/_glcanvas.cp312-win_arm64.pyd
wx/_grid.cp312-win_arm64.pyd
wx/_html.cp312-win_arm64.pyd
wx/_html2.cp312-win_arm64.pyd
wx/_media.cp312-win_arm64.pyd
wx/_msw.cp312-win_arm64.pyd
wx/_propgrid.cp312-win_arm64.pyd
wx/_ribbon.cp312-win_arm64.pyd
wx/_richtext.cp312-win_arm64.pyd
wx/_stc.cp312-win_arm64.pyd
wx/_xml.cp312-win_arm64.pyd
wx/_xrc.cp312-win_arm64.pyd
wx/adv.py
wx/adv.pyi
wx/aui.py
wx/aui.pyi
wx/core.py
wx/core.pyi
wx/dataview.py
wx/dataview.pyi
wx/gizmos.py
wx/glcanvas.py
wx/glcanvas.pyi
wx/grid.py
wx/grid.pyi
wx/html.py
wx/html.pyi
wx/html2.py
wx/html2.pyi
wx/media.py
wx/media.pyi
wx/msw.py
wx/msw.pyi
wx/propgrid.py
wx/propgrid.pyi
wx/ribbon.py
wx/ribbon.pyi
wx/richtext.py
wx/richtext.pyi
wx/siplib.cp312-win_arm64.pyd
wx/stc.py
wx/stc.pyi
wx/wxbase32u_net_vc140_arm64.dll
wx/wxbase32u_vc140_arm64.dll
wx/wxbase32u_xml_vc140_arm64.dll
wx/wxmsw32u_adv_vc140_arm64.dll
wx/wxmsw32u_aui_vc140_arm64.dll
wx/wxmsw32u_core_vc140_arm64.dll
wx/wxmsw32u_gl_vc140_arm64.dll
wx/wxmsw32u_html_vc140_arm64.dll
wx/wxmsw32u_media_vc140_arm64.dll
wx/wxmsw32u_propgrid_vc140_arm64.dll
wx/wxmsw32u_qa_vc140_arm64.dll
wx/wxmsw32u_ribbon_vc140_arm64.dll
wx/wxmsw32u_richtext_vc140_arm64.dll
wx/wxmsw32u_stc_vc140_arm64.dll
wx/wxmsw32u_webview_vc140_arm64.dll
wx/wxmsw32u_xrc_vc140_arm64.dll
wx/xml.py
wx/xml.pyi
wx/xrc.py
wx/xrc.pyi
wx/include/wxPython/sip.h
wx/include/wxPython/wxpy_api.h
wx/lib/CDate.py
wx/lib/ClickableHtmlWindow.py
wx/lib/__init__.py
wx/lib/activex.py
wx/lib/activexwrapper.py
wx/lib/anchors.py
wx/lib/busy.py
wx/lib/buttons.py
wx/lib/calendar.py
wx/lib/checkbox.py
wx/lib/colourdb.py
wx/lib/colourselect.py
wx/lib/colourutils.py
wx/lib/combotreebox.py
wx/lib/delayedresult.py
wx/lib/dialogs.py
wx/lib/docview.py
wx/lib/dragscroller.py
wx/lib/embeddedimage.py
wx/lib/eventStack.py
wx/lib/eventwatcher.py
wxpython-4.2.3.dist-info/licenses/LICENSE.txt
wxpython-4.2.3.dist-info/METADATA
wxpython-4.2.3.dist-info/WHEEL
wxpython-4.2.3.dist-info/entry_points.txt
wxpython-4.2.3.dist-info/top_level.txt
wxpython-4.2.3.dist-info/RECORD
