Metadata-Version: 2.4
Name: wxPython
Version: 4.2.3
Summary: Cross platform GUI toolkit for Python, "Phoenix" version
Author-email: Robin Dunn <robin@alldunn.com>, Scott Talbert <swt@techie.net>
License: wxWindows Library License (https://opensource.org/licenses/wxwindows.php)
Project-URL: Documentation, https://docs.wxpython.org/
Project-URL: Download, https://pypi.org/project/wxPython
Project-URL: Homepage, https://wxPython.org/
Project-URL: Source, https://github.com/wxWidgets/Phoenix
Project-URL: Repository, https://github.com/wxWidgets/Phoenix.git
Project-URL: Issues, https://github.com/wxWidgets/Phoenix/issues
Project-URL: Discuss, https://discuss.wxpython.org/
Keywords: GUI,awesome,cross-platform,user-interface,wx,wxWidgets,wxWindows
Platform: WIN32
Platform: WIN64
Platform: OSX
Platform: POSIX
Classifier: Development Status :: 6 - Mature
Classifier: Environment :: MacOS X :: Cocoa
Classifier: Environment :: Win32 (MS Windows)
Classifier: Environment :: X11 Applications :: GTK
Classifier: Intended Audience :: Developers
Classifier: License :: OSI Approved
Classifier: Operating System :: MacOS
Classifier: Operating System :: MacOS :: MacOS X
Classifier: Operating System :: Microsoft :: Windows
Classifier: Operating System :: Microsoft :: Windows :: Windows 7
Classifier: Operating System :: Microsoft :: Windows :: Windows 10
Classifier: Operating System :: Microsoft :: Windows :: Windows 11
Classifier: Operating System :: POSIX
Classifier: Operating System :: POSIX :: Linux
Classifier: Programming Language :: Python :: 3
Classifier: Programming Language :: Python :: 3.9
Classifier: Programming Language :: Python :: 3.10
Classifier: Programming Language :: Python :: 3.11
Classifier: Programming Language :: Python :: 3.12
Classifier: Programming Language :: Python :: 3.13
Classifier: Programming Language :: Python :: Implementation :: CPython
Classifier: Topic :: Software Development :: User Interfaces
Requires-Python: >=3.9
License-File: LICENSE.txt
Requires-Dist: numpy; python_version >= "3.0" and python_version < "3.12"
Requires-Dist: typing-extensions; python_version < "3.11"
Dynamic: description
Dynamic: description-content-type
Dynamic: license
Dynamic: license-file
Dynamic: platform
Dynamic: requires-dist
